{"username": "우와", "phase": 1, "intro_step": 1, "selected_room": null, "selected_drawer": null, "conversation_history": [], "room_conversation_count": 0, "drawer_conversation_count": 0, "letter_content": null, "stamp_image": null, "summary_text": "", "last_summary_messages_len": 0, "last_intent_key": null, "repeated_intent_count": 0, "crisis_cooldown": 0, "crisis_mode_active": false, "crisis_emotion_shown": false, "crisis_recovery_count": 0, "awaiting_room_change_confirm": false, "requested_new_room": null, "awaiting_reenter_confirm": false, "used_persona_stories": [], "used_persona_categories": [], "last_emotion": "기본"}